db_api_server/__init__.py
db_api_server/__main__.py
db_api_server/server.py
db_api_server-1.0.6.dist-info/LICENSE
db_api_server-1.0.6.dist-info/METADATA
db_api_server-1.0.6.dist-info/WHEEL
db_api_server-1.0.6.dist-info/entry_points.txt
db_api_server-1.0.6.dist-info/top_level.txt
db_api_server-1.0.6.dist-info/RECORD
